{
    "word_of_the_day": "Parcimonieux",
    "date": "December 07, 2025",
    "source_url": "https://www.dicolink.com/motdujour",
    "definitions": [
        {
            "source": "Grand Dictionnaire de la langue française numérisé",
            "definitions": [
                "adj. Qui fait preuve de parcimonie."
            ]
        },
        {
            "source": "Portail internet \"Le Dictionnaire\"",
            "definitions": [
                "Qui a de la parcimonie."
            ]
        }
    ]
}