{
    "word_of_the_day": "Spumeux",
    "date": "March 31, 2025",
    "source_url": "https://www.dicolink.com/motdujour",
    "definitions": [
        {
            "source": "Grand Dictionnaire de la langue française numérisé",
            "definitions": [
                "adj. Qui a l'apparence de l'écume."
            ]
        },
        {
            "source": "Portail internet \"Le Dictionnaire\"",
            "definitions": [
                "À l’aspect d’écume, qui est mêlé d’écume.",
                "Flou, étrange, bizarre, fatigué, et par extension mauvais ou raté."
            ]
        },
        {
            "source": "Wiktionnaire",
            "definitions": [
                "Écumeux.",
                "Flou, étrange, bizarre, fatigué, et par extension mauvais ou raté."
            ]
        }
    ]
}