{
    "word_of_the_day": "Aratoire",
    "date": "June 02, 2025",
    "source_url": "https://www.dicolink.com/motdujour",
    "definitions": [
        {
            "source": "Grand Dictionnaire de la langue française numérisé",
            "definitions": [
                "adj. Qui concerne le labourage, le travail du sol."
            ]
        },
        {
            "source": "Portail internet \"Le Dictionnaire\"",
            "definitions": [
                "Qui a rapport au labourage."
            ]
        },
        {
            "source": "Le littré",
            "definitions": [
                "adj. Qui sert ou qui se rapporte au labourage. Instruments aratoires. Travaux aratoires."
            ]
        },
        {
            "source": "Wiktionnaire",
            "definitions": [
                "Qui a rapport au labourage, ou aux espaces agricoles labourables."
            ]
        }
    ]
}