{
    "word_of_the_day": "Vitupérer",
    "date": "August 11, 2025",
    "source_url": "https://www.dicolink.com/motdujour",
    "definitions": [
        {
            "source": "Grand Dictionnaire de la langue française numérisé",
            "definitions": [
                "v. tr. Proférer des injures, des récriminations contre quelqu'un, quelque chose, les blâmer avec force : Vitupérer contre la hausse des prix."
            ]
        },
        {
            "source": "Portail internet \"Le Dictionnaire\"",
            "definitions": [
                "v.  (Transitif) (Littéraire) ou (Vieilli). Blâmer fortement et vivement.",
                "v.  (Intransitif) (Plus courant) Protester vivement, pester, invectiver contre quelque chose ou contre quelqu’un."
            ]
        },
        {
            "source": "Le littré",
            "definitions": [
                "v. tr.  Terme vieilli. Blâmer."
            ]
        }
    ]
}