{
    "word_of_the_day": "Vicinal",
    "date": "February 01, 2025",
    "source_url": "https://www.dicolink.com/motdujour",
    "definitions": [
        {
            "source": "Grand Dictionnaire de la langue française numérisé",
            "definitions": [
                "adj. Chemin vicinal, chemin qui met en communication des villages entre eux.",
                "n.m. En Belgique, tramway qui dessert la campagne ou la banlieue."
            ]
        },
        {
            "source": "Portail internet \"Le Dictionnaire\"",
            "definitions": [
                "(Littéraire) Qui concerne le voisinage.",
                "(Administration) Se dit des chemins qui servent de moyen de communication entre plusieurs villages."
            ]
        },
        {
            "source": "Wiktionnaire",
            "definitions": [
                "(Littéraire) Qui concerne le voisinage.",
                "(Administration) Se dit des chemins qui servent de moyen de communication entre plusieurs villages.",
                "(Stéréochimie) Qualifie deux groupes fonctionnels attachés à deux atomes de carbone adjacents.",
                "Chemin vicinal : qui relie deux villages voisins."
            ]
        }
    ]
}