{
    "word_of_the_day": "Brimborion",
    "date": "August 03, 2025",
    "source_url": "https://www.dicolink.com/motdujour",
    "definitions": [
        {
            "source": "Grand Dictionnaire de la langue française numérisé",
            "definitions": [
                "n.m. Littéraire. Chose de peu d'importance ou de peu de valeur ; babiole."
            ]
        },
        {
            "source": "Portail internet \"Le Dictionnaire\"",
            "definitions": [
                "n.  (Familier) Objet de peu de valeur."
            ]
        },
        {
            "source": "Wiktionnaire",
            "definitions": [
                "(Familier) Objet de peu de valeur.",
                "(Vieilli) (Argot) Couille Référence nécessaire."
            ]
        }
    ]
}